Workbook
Name aporte: 'FIIS Agents'!$D$16:$D$16
Name patrimonio: 'FIIS Agents'!$D$19:$D$19
Name qtd_anos: 'FIIS Agents'!$D$17:$D$17
Name rendimento_carteira: 'FIIS Agents'!$D$12:$D$12
Name salario: 'FIIS Agents'!$D$11:$D$11
Name sugestao_investimento: 'FIIS Agents'!$D$13:$D$13
Name taxa_mensal: 'FIIS Agents'!$D$18:$D$18

Sheet FIIS Agents
B10: CONFIGURAÇÕES
B11: Salário | D11: 5000
B12: Rendimento Carteira | D12: 0.009
B13: Sugestão de Investimento (30%) | D13: =D11*30% -> 1500
B15: INVESTIMENTO MENSAL
B16: Quanto Investir por Mês? | D16: 1500
B17: Por Quantos Anos? | D17: 2
B18: Taxa de Rendimento Mensal? | D18: 0.01079
B19: Patrimônio Acumulado? | D19: {=FV(taxa_mensal,qtd_anos*12,aporte*-1)} -> 40841.441
B20: Dividendos Mensais? | D20: {=patrimonio*rendimento_carteira} -> 367.57297
B22: Cenários | D22: Dividendo
B23: Quanto em 2 Anos? | C23: =FV($D$18,$A24*12,$D$16*-1) -> 40841.441 | D23: {=C23*rendimento_carteira} -> 367.57297
A24: 2 | B24: Quanto em 5 Anos? | C24: =FV($D$18,$A25*12,$D$16*-1) -> 125665.37 | D24: {=C24*rendimento_carteira} -> 1130.9883
A25: 5 | B25: Quanto em 10 Anos? | C25: =FV($D$18,$A26*12,$D$16*-1) -> 364926.32 | D25: {=C25*rendimento_carteira} -> 3284.3369
A26: 10 | B26: Quanto em 20 Anos? | C26: =FV($D$18,$A27*12,$D$16*-1) -> 1687797.6 | D26: {=C26*rendimento_carteira} -> 15190.178
A27: 20 | B27: Quanto em 30 Anos? | C27: =FV($D$18,$A28*12,$D$16*-1) -> 6483254.5 | D27: {=C27*rendimento_carteira} -> 58349.29
A28: 30
B30: PERFIL | C30: Moderado
B31: VALOR A SER INVESTIDO POR MÊS | C31: {=aporte} -> 1500
B33: TIPO DE FII | C33: Percentual Sugerido | D33: Valores
B34: PAPEL | C34: =VLOOKUP($C$30&"-"&B34,TBL_CHAVE!$A:$D,4,FALSE) -> 0.32 | D34: =C34*$C$31 -> 480
B35: TIJOLO | C35: =VLOOKUP($C$30&"-"&B35,TBL_CHAVE!$A:$D,4,FALSE) -> 0.35 | D35: =C35*$C$31 -> 525
B36: HÍBRIDOS | C36: =VLOOKUP($C$30&"-"&B36,TBL_CHAVE!$A:$D,4,FALSE) -> 0.08 | D36: =C36*$C$31 -> 120
B37: FOFs | C37: =VLOOKUP($C$30&"-"&B37,TBL_CHAVE!$A:$D,4,FALSE) -> 0.05 | D37: =C37*$C$31 -> 75
B38: DESENVOLVIMENTO | C38: =VLOOKUP($C$30&"-"&B38,TBL_CHAVE!$A:$D,4,FALSE) -> 0.1 | D38: =C38*$C$31 -> 150
B39: HOTELARIAS | C39: =VLOOKUP($C$30&"-"&B39,TBL_CHAVE!$A:$D,4,FALSE) -> 0.1 | D39: =C39*$C$31 -> 150
D40: =SUM(D34:D39) -> 1500

Sheet TBL_CHAVE
A2: CHAVE | B2: Perfil | C2: TIPO DE FII | D2: %
A3: =B3&"-"&C3 -> Conservador-PAPEL | B3: Conservador | C3: PAPEL | D3: 0.3 | I3: %
A4: =B4&"-"&C4 -> Conservador-TIJOLO | B4: Conservador | C4: TIJOLO | D4: 0.5 | G4: Moderado-TIJOLO | I4: =VLOOKUP(G4,$A:$D,4,FALSE) -> 0.35
A5: =B5&"-"&C5 -> Conservador-HÍBRIDOS | B5: Conservador | C5: HÍBRIDOS | D5: 0.1
A6: =B6&"-"&C6 -> Conservador-FOFs | B6: Conservador | C6: FOFs | D6: 0.1
A7: =B7&"-"&C7 -> Conservador-DESENVOLVIMENTO | B7: Conservador | C7: DESENVOLVIMENTO | D7: 0
A8: =B8&"-"&C8 -> Conservador-HOTELARIAS | B8: Conservador | C8: HOTELARIAS | D8: 0
A9: =B9&"-"&C9 -> Moderado-PAPEL | B9: Moderado | C9: PAPEL | D9: 0.32
A10: =B10&"-"&C10 -> Moderado-TIJOLO | B10: Moderado | C10: TIJOLO | D10: 0.35
A11: =B11&"-"&C11 -> Moderado-HÍBRIDOS | B11: Moderado | C11: HÍBRIDOS | D11: 0.08
A12: =B12&"-"&C12 -> Moderado-FOFs | B12: Moderado | C12: FOFs | D12: 0.05
A13: =B13&"-"&C13 -> Moderado-DESENVOLVIMENTO | B13: Moderado | C13: DESENVOLVIMENTO | D13: 0.1
A14: =B14&"-"&C14 -> Moderado-HOTELARIAS | B14: Moderado | C14: HOTELARIAS | D14: 0.1
A15: =B15&"-"&C15 -> Agressivo-PAPEL | B15: Agressivo | C15: PAPEL | D15: 0.5
A16: =B16&"-"&C16 -> Agressivo-TIJOLO | B16: Agressivo | C16: TIJOLO | D16: 0.1
... A20: =B20&"-"&C20 -> Agressivo-HOTELARIAS | B20: Agressivo | C20: HOTELARIAS | D20: 0.1
